avs_client/__init__.py
avs_client/avs_client/__init__.py
avs_client/avs_client/authentication.py
avs_client/avs_client/client.py
avs_client/avs_client/connection.py
avs_client/avs_client/device.py
avs_client/avs_client/helpers.py
avs_client/avs_client/ping.py
avs_client/demo/__init__.py
avs_client/demo/streaming_microphone.py
avs_client/refreshtoken/__init__.py
avs_client/refreshtoken/arg_parser.py
avs_client/refreshtoken/handlers.py
avs_client/refreshtoken/helpers.py
avs_client/refreshtoken/http_server.py
avs_client/refreshtoken/serve.py
avs_client-1.3.1.dist-info/LICENSE
avs_client-1.3.1.dist-info/METADATA
avs_client-1.3.1.dist-info/WHEEL
avs_client-1.3.1.dist-info/top_level.txt
avs_client-1.3.1.dist-info/RECORD
