Metadata-Version: 2.1
Name: avs-client
Version: 1.3.1
Summary: Python Client for Alexa Voice Service (AVS)
Home-page: https://github.com/richtier/alexa-voice-service-client
Author: Richard Tier
Author-email: rikatee@gmail.com
License: MIT
Platform: UNKNOWN
Classifier: Development Status :: 4 - Beta
Classifier: Environment :: Console
Classifier: Intended Audience :: Developers
Classifier: License :: OSI Approved :: MIT License
Classifier: Natural Language :: English
Classifier: Operating System :: OS Independent
Classifier: Programming Language :: Python :: 3.5
Classifier: Programming Language :: Python :: 3.6
Classifier: Programming Language :: Python :: Implementation :: PyPy
Classifier: Topic :: Software Development :: Libraries :: Python Modules
Requires-Dist: hyper (>=0.7.0<1.0.0)
Requires-Dist: requests-toolbelt (>=0.8.0<1.0.0)
Requires-Dist: requests (>=2.19.1<3.0.0)
Requires-Dist: resettabletimer (<1.0.0,>=0.6.3)
Provides-Extra: demo
Requires-Dist: pydub (<1.0.0,>=0.23.0) ; extra == 'demo'
Requires-Dist: pyaudio (<1.0.0,>=0.2.11) ; extra == 'demo'
Provides-Extra: test
Requires-Dist: flake8 (==3.4.0) ; extra == 'test'
Requires-Dist: freezegun (==0.3.9) ; extra == 'test'
Requires-Dist: pytest-cov (==2.5.1) ; extra == 'test'
Requires-Dist: pytest-sugar (==0.9.0) ; extra == 'test'
Requires-Dist: pytest (==3.2.0) ; extra == 'test'
Requires-Dist: requests-mock (==1.3.0) ; extra == 'test'
Requires-Dist: codecov (==2.0.9) ; extra == 'test'
Requires-Dist: twine (<2.0.0,>=1.11.0) ; extra == 'test'
Requires-Dist: wheel (<1.0.0,>=0.31.0) ; extra == 'test'
Requires-Dist: setuptools (<39.0.0,>=38.6.0) ; extra == 'test'
